reme_ai/__init__.py
reme_ai/main.py
reme_ai/agent/__init__.py
reme_ai/agent/react/__init__.py
reme_ai/agent/react/agentic_retrieve_op.py
reme_ai/agent/react/agentic_retrieve_prompt.yaml
reme_ai/agent/react/simple_react_op.py
reme_ai/agent/tools/__init__.py
reme_ai/agent/tools/llm_mock_search_op.py
reme_ai/agent/tools/llm_mock_search_prompt.yaml
reme_ai/agent/tools/mock_search_tools.py
reme_ai/agent/tools/use_mock_search_op.py
reme_ai/config/__init__.py
reme_ai/config/config_parser.py
reme_ai/config/default.yaml
reme_ai/constants/__init__.py
reme_ai/constants/common_constants.py
reme_ai/constants/language_constants.py
reme_ai/core/__init__.py
reme_ai/core/application.py
reme_ai/core/main.py
reme_ai/core/reme.py
reme_ai/core/config/__init__.py
reme_ai/core/config/default.yaml
reme_ai/core/config/reme_config_parser.py
reme_ai/core/context/__init__.py
reme_ai/core/context/base_context.py
reme_ai/core/context/prompt_handler.py
reme_ai/core/context/registry.py
reme_ai/core/context/runtime_context.py
reme_ai/core/context/service_context.py
reme_ai/core/embedding/__init__.py
reme_ai/core/embedding/base_embedding_model.py
reme_ai/core/embedding/openai_embedding_model.py
reme_ai/core/embedding/openai_embedding_model_sync.py
reme_ai/core/enumeration/__init__.py
reme_ai/core/enumeration/chunk_enum.py
reme_ai/core/enumeration/http_enum.py
reme_ai/core/enumeration/json_schema_enum.py
reme_ai/core/enumeration/memory_type.py
reme_ai/core/enumeration/registry_enum.py
reme_ai/core/enumeration/role.py
reme_ai/core/flow/__init__.py
reme_ai/core/flow/base_flow.py
reme_ai/core/flow/cmd_flow.py
reme_ai/core/flow/expression_flow.py
reme_ai/core/llm/__init__.py
reme_ai/core/llm/base_llm.py
reme_ai/core/llm/lite_llm.py
reme_ai/core/llm/lite_llm_sync.py
reme_ai/core/llm/openai_llm.py
reme_ai/core/llm/openai_llm_sync.py
reme_ai/core/op/__init__.py
reme_ai/core/op/base_op.py
reme_ai/core/op/base_ray_op.py
reme_ai/core/op/parallel_op.py
reme_ai/core/op/sequential_op.py
reme_ai-0.2.0.5.dist-info/licenses/LICENSE
reme_ai-0.2.0.5.dist-info/METADATA
reme_ai-0.2.0.5.dist-info/WHEEL
reme_ai-0.2.0.5.dist-info/entry_points.txt
reme_ai-0.2.0.5.dist-info/top_level.txt
reme_ai-0.2.0.5.dist-info/RECORD
