Metadata-Version: 2.4
Name: reme_ai
Version: 0.2.0.5
Summary: Remember Me, Refine Me.
Author-email: "jinli.yl" <jinli.yl@alibaba-inc.com>, "dengjiaji.djj" <dengjiaji.djj@alibaba-inc.com>, "caozouying.czy" <caozouying.czy@alibaba-inc.com>, "weikangzhou.zwk" <weikangzhou.zwk@alibaba-inc.com>
License:                                  Apache License
Project-URL: Homepage, https://github.com/agentscope-ai/ReMe
Project-URL: Documentation, https://reme.agentscope.io/
Project-URL: Repository, https://github.com/agentscope-ai/ReMe
Keywords: llm,memory,experience,memoryscope,ai,mcp,http
Classifier: Development Status :: 4 - Beta
Classifier: Intended Audience :: Developers
Classifier: Intended Audience :: Science/Research
Classifier: License :: OSI Approved :: Apache Software License
Classifier: Operating System :: OS Independent
Classifier: Programming Language :: Python :: 3
Classifier: Programming Language :: Python :: 3.10
Classifier: Topic :: Scientific/Engineering :: Artificial Intelligence
Classifier: Topic :: Software Development :: Libraries :: Python Modules
Classifier: Topic :: Software Development :: Libraries :: Application Frameworks
Classifier: Typing :: Typed
Requires-Python: >=3.10
License-File: LICENSE
Requires-Dist: flowllm[reme]>=0.2.0.9
Provides-Extra: dev
Requires-Dist: jupyter-book; extra == "dev"
Requires-Dist: ghp-import; extra == "dev"
Requires-Dist: myst-nb; extra == "dev"
Requires-Dist: sphinxcontrib-bibtex; extra == "dev"
Requires-Dist: furo; extra == "dev"
Requires-Dist: sphinxcontrib-mermaid; extra == "dev"
Requires-Dist: pre-commit; extra == "dev"
Provides-Extra: token
Requires-Dist: flowllm[token]>=0.2.0.9; extra == "token"
Provides-Extra: full
Requires-Dist: reme_ai[dev,token]; extra == "full"
Dynamic: license-file
